mcp_server_ietf/__init__.py
mcp_server_ietf/rfc_parser.py
mcp_server_ietf/server.py
iflow_mcp_mcp_server_ietf-0.1.0.dist-info/METADATA
iflow_mcp_mcp_server_ietf-0.1.0.dist-info/WHEEL
iflow_mcp_mcp_server_ietf-0.1.0.dist-info/entry_points.txt
iflow_mcp_mcp_server_ietf-0.1.0.dist-info/licenses/LICENSE
iflow_mcp_mcp_server_ietf-0.1.0.dist-info/RECORD
