Metadata-Version: 2.4
Name: iflow-mcp_mcp-server-ietf
Version: 0.1.0
Summary: A Model Context Protocol server for fetching ietf documents for LLMs
License: MIT
License-File: LICENSE
Requires-Python: >=3.11
Requires-Dist: mcp[cli]>=1.3.0
Requires-Dist: python-dotenv>=1.0.1
Requires-Dist: requests>=2.32.3
